pollination/honeybee_radiance_postprocess/__init__.py
pollination/honeybee_radiance_postprocess/abnt.py
pollination/honeybee_radiance_postprocess/breeam.py
pollination/honeybee_radiance_postprocess/grid.py
pollination/honeybee_radiance_postprocess/leed.py
pollination/honeybee_radiance_postprocess/merge.py
pollination/honeybee_radiance_postprocess/mtxop.py
pollination/honeybee_radiance_postprocess/post_process.py
pollination/honeybee_radiance_postprocess/sky.py
pollination/honeybee_radiance_postprocess/translate.py
pollination/honeybee_radiance_postprocess/two_phase.py
pollination/honeybee_radiance_postprocess/viewfactor.py
pollination/honeybee_radiance_postprocess/well.py
pollination_honeybee_radiance_postprocess-0.0.94.dist-info/LICENSE
pollination_honeybee_radiance_postprocess-0.0.94.dist-info/METADATA
pollination_honeybee_radiance_postprocess-0.0.94.dist-info/WHEEL
pollination_honeybee_radiance_postprocess-0.0.94.dist-info/top_level.txt
pollination_honeybee_radiance_postprocess-0.0.94.dist-info/RECORD
