Metadata-Version: 2.1
Name: pollination-honeybee-radiance-postprocess
Version: 0.0.94
Summary: Honeybee Radiance Post Process plugin for Pollination.
Home-page: https://github.com/pollination/pollination-honeybee-radiance-postprocess
Author: ladybug-tools
Author-email: info@ladybug.tools
Maintainer: mikkel, ladybug-tools
Maintainer-email: mikkel@ladybug.tools, info@ladybug.tools
License: PolyForm Shield License 1.0.0, https://polyformproject.org/wp-content/uploads/2020/06/PolyForm-Shield-1.0.0.txt
Project-URL: icon, https://raw.githubusercontent.com/ladybug-tools/artwork/master/icons_bugs/grasshopper_tabs/HB-Radiance.png
Project-URL: docker, https://hub.docker.com/r/ladybugtools/honeybee-radiance-postprocess
Keywords: honeybee,radiance,ladybug-tools,daylight
License-File: LICENSE
Requires-Dist: pollination-dsl>=0.15.3
Requires-Dist: honeybee-radiance-postprocess>=0.4.548
